Metadata-Version: 2.1
Name: ChemoBiolysis
Version: 0.0.3
Summary: ChemoBiolysis: A Comprehensive Python Package for Chemical and Biological Analysis
Home-page: https://github.com/ahmed1212212/ChemoBiolysis.git
Author: Ahmed Alhilal
Author-email: aalhilal@udel.edu
License: MIT
Keywords: Cheminformatics
Classifier: Development Status :: 5 - Production/Stable
Classifier: Intended Audience :: Education
Classifier: Operating System :: Microsoft :: Windows :: Windows 10
Classifier: License :: OSI Approved :: MIT License
Classifier: Programming Language :: Python :: 3
License-File: LICENCE.txt
